kyauthlib/__init__.py
kyauthlib/consts.py
kyauthlib/deprecate.py
kyauthlib/common/__init__.py
kyauthlib/common/encoding.py
kyauthlib/common/errors.py
kyauthlib/common/security.py
kyauthlib/common/urls.py
kyauthlib/integrations/__init__.py
kyauthlib/integrations/base_client/__init__.py
kyauthlib/integrations/base_client/async_app.py
kyauthlib/integrations/base_client/async_openid.py
kyauthlib/integrations/base_client/errors.py
kyauthlib/integrations/base_client/framework_integration.py
kyauthlib/integrations/base_client/registry.py
kyauthlib/integrations/base_client/sync_app.py
kyauthlib/integrations/base_client/sync_openid.py
kyauthlib/integrations/django_client/__init__.py
kyauthlib/integrations/django_client/apps.py
kyauthlib/integrations/django_client/integration.py
kyauthlib/integrations/django_oauth1/__init__.py
kyauthlib/integrations/django_oauth1/authorization_server.py
kyauthlib/integrations/django_oauth1/nonce.py
kyauthlib/integrations/django_oauth1/resource_protector.py
kyauthlib/integrations/django_oauth2/__init__.py
kyauthlib/integrations/django_oauth2/authorization_server.py
kyauthlib/integrations/django_oauth2/endpoints.py
kyauthlib/integrations/django_oauth2/requests.py
kyauthlib/integrations/django_oauth2/resource_protector.py
kyauthlib/integrations/django_oauth2/signals.py
kyauthlib/integrations/flask_client/__init__.py
kyauthlib/integrations/flask_client/apps.py
kyauthlib/integrations/flask_client/integration.py
kyauthlib/integrations/flask_oauth1/__init__.py
kyauthlib/integrations/flask_oauth1/authorization_server.py
kyauthlib/integrations/flask_oauth1/cache.py
kyauthlib/integrations/flask_oauth1/resource_protector.py
kyauthlib/integrations/flask_oauth2/__init__.py
kyauthlib/integrations/flask_oauth2/authorization_server.py
kyauthlib/integrations/flask_oauth2/errors.py
kyauthlib/integrations/flask_oauth2/requests.py
kyauthlib/integrations/flask_oauth2/resource_protector.py
kyauthlib/integrations/flask_oauth2/signals.py
kyauthlib-0.0.5.dist-info/LICENSE
kyauthlib-0.0.5.dist-info/METADATA
kyauthlib-0.0.5.dist-info/WHEEL
kyauthlib-0.0.5.dist-info/top_level.txt
kyauthlib-0.0.5.dist-info/RECORD
