Metadata-Version: 2.2
Name: kyAuthlib
Version: 0.0.5
Summary: The ultimate Python library in building OAuth and OpenID Connect servers and clients.
Home-page: https://authlib.org/
Author: Hsiaoming Yang
Author-email: me@lepture.com
License: BSD 3-Clause License
Project-URL: Documentation, https://docs.authlib.org/
Project-URL: Commercial License, https://authlib.org/plans
Project-URL: Bug Tracker, https://github.com/lepture/authlib/issues
Project-URL: Source Code, https://github.com/lepture/authlib
Project-URL: Donate, https://github.com/sponsors/lepture
Project-URL: Blog, https://blog.authlib.org/
Platform: any
Classifier: Development Status :: 5 - Production/Stable
Classifier: Environment :: Console
Classifier: Environment :: Web Environment
Classifier: Framework :: Flask
Classifier: Framework :: Django
Classifier: Intended Audience :: Developers
Classifier: License :: OSI Approved :: BSD License
Classifier: Operating System :: OS Independent
Classifier: Programming Language :: Python
Classifier: Programming Language :: Python :: 3
Classifier: Programming Language :: Python :: 3.7
Classifier: Programming Language :: Python :: 3.8
Classifier: Programming Language :: Python :: 3.9
Classifier: Programming Language :: Python :: 3.10
Classifier: Programming Language :: Python :: 3.11
Classifier: Topic :: Internet :: WWW/HTTP :: Dynamic Content
Classifier: Topic :: Internet :: WWW/HTTP :: WSGI :: Application
License-File: LICENSE
Requires-Dist: cryptography>=3.2
Dynamic: requires-dist
